shipyard_domo/__init__.py
shipyard_domo/cli/__init__.py
shipyard_domo/cli/authtest.py
shipyard_domo/cli/download_dataset.py
shipyard_domo/cli/export_card_to_file.py
shipyard_domo/cli/refresh_dataset.py
shipyard_domo/cli/upload.py
shipyard_domo/domo.py
shipyard_domo/utils/exceptions.py
shipyard_domo/utils/utils.py
shipyard_domo-0.2.1.dist-info/METADATA
shipyard_domo-0.2.1.dist-info/WHEEL
shipyard_domo-0.2.1.dist-info/RECORD
