Metadata-Version: 2.1
Name: shipyard-domo
Version: 0.2.1
Summary: A local client for connecting and working with Domo
License: Apache 2.0
Author: wrp801
Author-email: wespoulsen@gmail.com
Requires-Python: >=3.9,<4.0
Classifier: License :: Other/Proprietary License
Classifier: Programming Language :: Python :: 3
Classifier: Programming Language :: Python :: 3.9
Classifier: Programming Language :: Python :: 3.10
Classifier: Programming Language :: Python :: 3.11
Requires-Dist: pandas (>=2.0,<3.0)
Requires-Dist: pydomo (>=0.3.0.9,<0.4.0.0)
Requires-Dist: requests (==2.31.0)
Requires-Dist: shipyard-bp-utils (==1.0.3)
Requires-Dist: shipyard-templates (==0.6.2)
